remote/entrypoints.py
remote/exceptions.py
remote/explain.py
remote/file_changes.py
remote/py.typed
remote/util.py
remote/workspace.py
remote/configuration/__init__.py
remote/configuration/classic.py
remote/configuration/discovery.py
remote/configuration/shared.py
remote/configuration/toml.py
remote_exec_api-1.13.3.dist-info/LICENSE
remote_exec_api-1.13.3.dist-info/METADATA
remote_exec_api-1.13.3.dist-info/WHEEL
remote_exec_api-1.13.3.dist-info/entry_points.txt
remote_exec_api-1.13.3.dist-info/top_level.txt
remote_exec_api-1.13.3.dist-info/RECORD
