Metadata-Version: 2.1
Name: remote-exec-api
Version: 1.13.3
Summary: A CLI to sync codebases and execute commands remotely
Home-page: https://github.com/remote-cli/remote
Author: Evgeny Barbashov
License: BSD-2-CLAUSE
Classifier: Development Status :: 5 - Production/Stable
Classifier: Programming Language :: Python
Classifier: Programming Language :: Python :: 3
Classifier: Programming Language :: Python :: 3 :: Only
Classifier: Programming Language :: Python :: 3.6
Classifier: Programming Language :: Python :: 3.7
Classifier: Programming Language :: Python :: 3.8
Classifier: Intended Audience :: Developers
Classifier: Intended Audience :: Information Technology
Classifier: Intended Audience :: System Administrators
Classifier: License :: OSI Approved
Classifier: License :: OSI Approved :: BSD License
Classifier: Operating System :: Unix
Classifier: Operating System :: POSIX :: Linux
Classifier: Environment :: Console
Classifier: Environment :: MacOS X
Classifier: Topic :: Software Development
Requires-Python: >=3.9
License-File: LICENSE
Requires-Dist: click ==8.1.7
Requires-Dist: toml ==0.10.2
Requires-Dist: pydantic ==2.6.1
Requires-Dist: watchdog ==4.0.0
